jvcurrtime/__init__.py
jvcurrtime/currtime.py
jvcurrtime-1.0.5.dist-info/licenses/LICENSE
jvcurrtime-1.0.5.dist-info/METADATA
jvcurrtime-1.0.5.dist-info/WHEEL
jvcurrtime-1.0.5.dist-info/top_level.txt
jvcurrtime-1.0.5.dist-info/RECORD
